tvDatafeed/__init__.py
tvDatafeed/consumer.py
tvDatafeed/datafeed.py
tvDatafeed/main.py
tvDatafeed/py.typed
tvDatafeed/seis.py
tvdatafeed_enhanced-2.2.0.dist-info/licenses/LICENSE
tvdatafeed_enhanced-2.2.0.dist-info/METADATA
tvdatafeed_enhanced-2.2.0.dist-info/WHEEL
tvdatafeed_enhanced-2.2.0.dist-info/top_level.txt
tvdatafeed_enhanced-2.2.0.dist-info/RECORD
