Metadata-Version: 2.4
Name: tvdatafeed-enhanced
Version: 2.2.0
Summary: TradingView historical and live data downloader with advanced features
Author: StreamAlpha, rongardF
License-Expression: MIT
Project-URL: Homepage, https://github.com/rongardF/tvdatafeed/
Project-URL: Documentation, https://github.com/rongardF/tvdatafeed/blob/main/README.md
Project-URL: Source, https://github.com/rongardF/tvdatafeed/
Project-URL: Tracker, https://github.com/rongardF/tvdatafeed/issues
Keywords: tradingview,trading,data,market-data,finance,stocks,crypto,forex,live-data,real-time
Classifier: Development Status :: 4 - Beta
Classifier: Intended Audience :: Developers
Classifier: Intended Audience :: Financial and Insurance Industry
Classifier: Programming Language :: Python :: 3
Classifier: Programming Language :: Python :: 3.10
Classifier: Programming Language :: Python :: 3.11
Classifier: Programming Language :: Python :: 3.12
Classifier: Programming Language :: Python :: 3.13
Classifier: Topic :: Office/Business :: Financial
Classifier: Topic :: Office/Business :: Financial :: Investment
Classifier: Topic :: Software Development :: Libraries :: Python Modules
Classifier: Operating System :: OS Independent
Requires-Python: >=3.10
License-File: LICENSE
Requires-Dist: pandas>=2.2.0
Requires-Dist: websockets>=14.1
Requires-Dist: requests>=2.32.0
Requires-Dist: python-dateutil>=2.8.0
Provides-Extra: captcha
Requires-Dist: browser-cookie3>=0.19.1; extra == "captcha"
Dynamic: license-file
